raynest/parameter.cpython-312-darwin.so
raynest-1.1.2.dist-info/licenses/LICENSE
tests/__init__.py
tests/test_1d.py
tests/test_2d.py
tests/test_2d_hmc.py
tests/test_2d_slice.py
tests/test_gaussian.py
tests/test_half_gaussian.py
tests/test_ring.py
tests/test_ring_slice.py
tests/test_verbosity.py
raynest-1.1.2.dist-info/METADATA
raynest-1.1.2.dist-info/WHEEL
raynest-1.1.2.dist-info/top_level.txt
raynest-1.1.2.dist-info/RECORD
