Metadata-Version: 2.4
Name: raynest
Version: 1.1.2
Summary: raynest: Parallel nested sampling based on ray
Home-page: https://github.com/wdpozzo/raynest
Author-email: Walter Del Pozzo <walter.delpozzo@ligo.org>, John Veitch <john.veitch@ligo.org>
License: MIT License
Project-URL: Homepage, https://github.com/wdpozzo/raynest
Project-URL: Repository, https://github.com/wdpozzo/raynest
Keywords: nested,sampling,bayesian,inference
Requires-Python: >=3.9
License-File: LICENSE
Requires-Dist: numpy
Requires-Dist: scipy
Requires-Dist: corner
Requires-Dist: tqdm
Requires-Dist: matplotlib
Requires-Dist: ray
Requires-Dist: h5py
Requires-Dist: psutil
Requires-Dist: setuptools
Dynamic: home-page
Dynamic: license-file
Dynamic: requires-python
